infrahub_mcp/__init__.py
infrahub_mcp/constants.py
infrahub_mcp/server.py
infrahub_mcp/utils.py
infrahub_mcp/prompts/main.md
infrahub_mcp/resources/__init__.py
infrahub_mcp/tools/__init__.py
infrahub_mcp/tools/branch.py
infrahub_mcp/tools/gql.py
infrahub_mcp/tools/nodes.py
infrahub_mcp/tools/schema.py
infrahub_mcp-0.1.2.dist-info/METADATA
infrahub_mcp-0.1.2.dist-info/WHEEL
infrahub_mcp-0.1.2.dist-info/licenses/LICENSE.txt
infrahub_mcp-0.1.2.dist-info/RECORD
