Metadata-Version: 2.4
Name: infrahub-mcp
Version: 0.1.2
Summary: MCP server to interact with Infrahub
License-File: LICENSE.txt
Requires-Python: >=3.13
Requires-Dist: fastmcp>=2.10.5
Requires-Dist: infrahub-sdk>=1.13.5
